{
  "string": [
    {
      "name": "permissionmanager_MainAbility",
      "value": "权限管理"
    },
    {
      "name": "description_mainability",
      "value": "权限管理"
    },
    {
      "name": "permissionmanager_GrantAbility",
      "value": "权限申请"
    },
    {
      "name": "no_permission",
      "value": "暂无权限"
    },
    {
      "name": "access_permission",
      "value": "访问权限"
    },
    {
      "name": "permission_access_record",
      "value": "权限访问记录"
    },
    {
      "name": "authority_management",
      "value": "权限管理"
    },
    {
      "name": "other_permissions",
      "value": "其它权限"
    },
    {
      "name": "application",
      "value": "应用"
    },
    {
      "name": "authority",
      "value": "权限"
    },
    {
      "name": "textInput_placeholder",
      "value": "搜索应用"
    },
    {
      "name": "allowed",
      "value": "已允许"
    },
    {
      "name": "banned",
      "value": "已禁止"
    },
    {
      "name": "description_grantability",
      "value": "权限申请"
    },
    {
      "name": "Authorization_failed",
      "value": "授权失败！"
    },
    {
      "name": "reason_suffix",
      "value": "等权限。"
    },
    {
      "name": "separator",
      "value": "、"
    },
    {
      "name": "visits",
      "value": "访问次数："
    },
    {
      "name": "recent_visit",
      "value": "；最近访问："
    },
    {
      "name": "morning",
      "value": "上午"
    },
    {
      "name": "afternoon",
      "value": "下午"
    }
  ]
}