{
  "string": [
    {
      "name": "permissionmanager_desc",
      "value": "权限管理"
    },
    {
      "name": "MainAbility_desc",
      "value": "从权限和应用两个维度来管理所有应用申请的权限。"
    },
    {
      "name": "MainAbility_label",
      "value": "权限管理"
    },
    {
      "name": "no_permission",
      "value": "暂无权限"
    },
    {
      "name": "access_permission",
      "value": "访问权限"
    },
    {
      "name": "permission_access_record",
      "value": "权限访问记录"
    },
    {
      "name": "authority_management",
      "value": "权限管理"
    },
    {
      "name": "other_permissions",
      "value": "其它权限"
    },
    {
      "name": "application",
      "value": "应用"
    },
    {
      "name": "authority",
      "value": "权限"
    },
    {
      "name": "textInput_placeholder",
      "value": "搜索应用"
    },
    {
      "name": "allowed",
      "value": "已允许"
    },
    {
      "name": "banned",
      "value": "已禁止"
    },
    {
      "name": "Authorization_failed",
      "value": "授权失败！"
    },
    {
      "name": "reason_suffix",
      "value": "等权限。"
    },
    {
      "name": "separator",
      "value": "、"
    },
    {
      "name": "visits",
      "value": "访问次数："
    },
    {
      "name": "recent_visit",
      "value": "；最近访问："
    },
    {
      "name": "morning",
      "value": "上午"
    },
    {
      "name": "afternoon",
      "value": "下午"
    },
    {
      "name": "no_record",
      "value": "没有权限访问记录"
    },
    {
      "name": "record_time_limit",
      "value": "近7天访问记录"
    },
    {
      "name": "allow",
      "value": "允许"
    },
    {
      "name": "ban",
      "value": "禁止"
    },
    {
      "name": "precise_location",
      "value": "精确位置"
    },
    {
      "name": "precise_location_on",
      "value": "精确位置：开启"
    },
    {
      "name": "precise_location_off",
      "value": "精确位置：关闭"
    },
    {
      "name": "get_the_exact_position",
      "value": "允许该应用获取您的准确位置。关闭后，应用获取的位置会有偏差。"
    },
    {
      "name": "close_exact_position",
      "value": "关闭精确位置后，应用获取的位置会有偏差。"
    },
    {
      "name": "whether_to_allow",
      "value": "是否允许"
    },
    {
      "name": "access_general_location",
      "value": "访问大致位置？"
    },
    {
      "name": "fuzzy_to_exact",
      "value": "的位置访问权限从“大致位置”改为“精确位置”？"
    }
  ]
}